langchain_apify/__init__.py
langchain_apify/const.py
langchain_apify/document_loaders.py
langchain_apify/error_messages.py
langchain_apify/py.typed
langchain_apify/tools.py
langchain_apify/utils.py
langchain_apify/wrappers.py
langchain_apify-0.1.4.dist-info/LICENSE
langchain_apify-0.1.4.dist-info/METADATA
langchain_apify-0.1.4.dist-info/WHEEL
langchain_apify-0.1.4.dist-info/RECORD
