Metadata-Version: 2.3
Name: langchain-apify
Version: 0.1.4
Summary: An integration package connecting Apify and LangChain
License: Apache-2.0
Author: Apify Technologies s.r.o.
Author-email: support@apify.com
Requires-Python: >=3.9,<4.0
Classifier: License :: OSI Approved :: Apache Software License
Classifier: Programming Language :: Python :: 3
Classifier: Programming Language :: Python :: 3.9
Classifier: Programming Language :: Python :: 3.10
Classifier: Programming Language :: Python :: 3.11
Classifier: Programming Language :: Python :: 3.12
Classifier: Programming Language :: Python :: 3.13
Requires-Dist: apify-client (>=1.8.1,<2.0.0)
Requires-Dist: eval-type-backport (>=0.2.2,<0.3.0)
Requires-Dist: langchain-core (>=0.3.15,<0.4.0)
Project-URL: Apify Homepage, https://apify.com
Project-URL: Issue Tracker, https://github.com/apify/langchain-apify/issues
Project-URL: Repository, https://github.com/apify/langchain-apify
Project-URL: Release Notes, https://github.com/apify/langchain-apify/releases?expanded=true
Project-URL: Source Code, https://github.com/apify/langchain-apify/tree/main/
